{
    "id": "swimming",
    "name": "Swimming",
    "icon": "ios-water",
    "category": "water",
    "sort_order": 7,
    "gps_default": false,
    "barometer_default": false,
    "sensors": ["heart_rate", "accelerometer"],
    "data_screens": ["default_timer", "default_hr"],
    "metrics": ["calories", "hrv_rmssd"],
    "power_profiles": {
        "low_power":  { "hr_interval_ms": 10000 },
        "balanced":   { "hr_interval_ms": 5000  },
        "high_perf":  { "hr_interval_ms": 2000  },
        "ultra":      { "hr_interval_ms": 1000  }
    }
}
